pytransifex/__init__.py
pytransifex/__main__.py
pytransifex/api.py
pytransifex/cli.py
pytransifex/config.py
pytransifex/exceptions.py
pytransifex/interfaces.py
pytransifex/utils.py
pytransifex-1.1.5.dist-info/LICENSE
pytransifex-1.1.5.dist-info/METADATA
pytransifex-1.1.5.dist-info/WHEEL
pytransifex-1.1.5.dist-info/entry_points.txt
pytransifex-1.1.5.dist-info/top_level.txt
pytransifex-1.1.5.dist-info/RECORD
