Metadata-Version: 2.1
Name: pytransifex
Version: 1.1.5
Summary: Yet another Python Transifex API.
Author-email: Denis Rouzaud <denis@opengis.ch>, Adrien Glauser <adrien@opengis.ch>
License: GPLv3
Project-URL: homepage, https://github.com/opengisch/pytransifex
Keywords: transifex
Classifier: Topic :: Software Development :: Localization
Classifier: License :: OSI Approved :: GNU General Public License v3 or later (GPLv3+)
Classifier: Programming Language :: Python :: 3
Requires-Python: >=3.10
License-File: LICENSE
Requires-Dist: requests
Requires-Dist: click
Requires-Dist: transifex-python
Requires-Dist: python-dotenv
Requires-Dist: toml
